pymcdc/__init__.py
pymcdc/__main__.py
pymcdc/cli.py
pymcdc/decisao.py
pymcdc/transform_log.py
pymcdc/visit_dot.py
pymcdc/visit_log.py
pymcdc-0.2.dist-info/licenses/LICENSE
pymcdc-0.2.dist-info/METADATA
pymcdc-0.2.dist-info/WHEEL
pymcdc-0.2.dist-info/entry_points.txt
pymcdc-0.2.dist-info/top_level.txt
pymcdc-0.2.dist-info/RECORD
