Metadata-Version: 2.4
Name: pymcdc
Version: 0.2
Summary: MC/DC analizer for Python
Author: Delamaro
Author-email: Delamaro <delamaro@icmc.usp.br>
Requires-Python: >=3.10
License-File: LICENSE
Dynamic: author
Dynamic: license-file
